mongo_dynamic_models/__init__.py
mongo_dynamic_models/core/__init__.py
mongo_dynamic_models/version/version.json
mongo_models/__init__.py
mongo_models/core/__init__.py
mongo_dynamic_models-1.0.1.dist-info/METADATA
mongo_dynamic_models-1.0.1.dist-info/WHEEL
mongo_dynamic_models-1.0.1.dist-info/top_level.txt
mongo_dynamic_models-1.0.1.dist-info/RECORD
