Metadata-Version: 2.1
Name: mongo-dynamic-models
Version: 1.0.1
Summary: generate mongo models automatically with mongoengine
Home-page: https://www.github.com/suqingdong/mongo_dynamic_models
Author: suqingdong
Author-email: suqingdong1114@gmail.com
License: BSD License
Platform: UNKNOWN
Classifier: Operating System :: OS Independent
Classifier: Intended Audience :: Developers
Classifier: License :: OSI Approved :: BSD License
Classifier: Programming Language :: Python
Classifier: Programming Language :: Python :: 3
Classifier: Programming Language :: Python :: 3 :: Only
Classifier: Programming Language :: Python :: 3.8
Classifier: Programming Language :: Python :: 3.9
Classifier: Topic :: Software Development :: Libraries
Requires-Dist: mongoengine
